gptmodel/__init__.py
gptmodel/gptmodel.py
gptmodel-1.0.8.dist-info/LICENSE.txt
gptmodel-1.0.8.dist-info/METADATA
gptmodel-1.0.8.dist-info/WHEEL
gptmodel-1.0.8.dist-info/top_level.txt
gptmodel-1.0.8.dist-info/RECORD
